<Properties StartupConfiguration="{DDFBC18F-9396-3137-9CFE-DEB2CDB74636}|">
  <MonoDevelop.Ide.Workbench ActiveDocument="Assets/Move.cs">
    <Files>
      <File FileName="Assets/PipesMove.cs" Line="8" Column="28" />
    </Files>
    <Pads>
      <Pad Id="ProjectPad">
        <State name="__root__">
          <Node name="Game" expanded="True">
            <Node name="Assets" expanded="True" />
          </Node>
        </State>
      </Pad>
    </Pads>
  </MonoDevelop.Ide.Workbench>
  <MonoDevelop.Ide.DebuggingService.Breakpoints>
    <BreakpointStore />
  </MonoDevelop.Ide.DebuggingService.Breakpoints>
  <MultiItemStartupConfigurations />
  <MonoDevelop.Ide.ItemProperties.Assembly-CSharp PreferredExecutionTarget="8202db64-6422-48ab-a6cb-2a23f951e0b9" />
  <MonoDevelop.Ide.Workspace ActiveConfiguration="Debug" />
  <MonoDevelop.Ide.DebuggingService.PinnedWatches />
</Properties>